sunmat/__init__.py
sunmat/sunmat.py
suNmat-0.0.0.dist-info/METADATA
suNmat-0.0.0.dist-info/WHEEL
suNmat-0.0.0.dist-info/top_level.txt
suNmat-0.0.0.dist-info/RECORD
