Metadata-Version: 2.1
Name: suNmat
Version: 0.0.0
Summary: Parameterized unitary rotations
Home-page: https://github.com/audunsh/sunmat
Author: Audun Skau Hansen
Author-email: a.s.hansen@kjemi.uio.no
License: UNKNOWN
Platform: UNKNOWN
Classifier: Programming Language :: Python :: 3
Classifier: License :: OSI Approved :: MIT License
Classifier: Operating System :: OS Independent
